dnstoolbox/__init__.py
dnstoolbox/domains/README.md
dnstoolbox/domains/__init__.py
dnstoolbox/domains/suffixes.py
dnstoolbox/domains/whois.py
dnstoolbox/misc.py
dnstoolbox/records/README.md
dnstoolbox/records/__init__.py
dnstoolbox/records/cname.py
dnstoolbox/records/dkim.py
dnstoolbox/records/dmarc.py
dnstoolbox/records/records.py
dnstoolbox/records/spf.py
dnstoolbox/records/utils.py
dnstoolbox/zones/README.md
dnstoolbox/zones/__init__.py
dnstoolbox/zones/nameservers.py
dnstoolbox/zones/operation.py
dnstoolbox/zones/zonefile.py
dnstoolbox-0.1.0.dist-info/LICENSE
dnstoolbox-0.1.0.dist-info/METADATA
dnstoolbox-0.1.0.dist-info/WHEEL
dnstoolbox-0.1.0.dist-info/RECORD
