Metadata-Version: 2.1
Name: dnstoolbox
Version: 0.1.0
Summary: 
Author: David Gallay
Author-email: david.gallay.96@gmail.com
Requires-Python: >=3.9.0,<4.0.0
Classifier: Programming Language :: Python :: 3
Classifier: Programming Language :: Python :: 3.9
Classifier: Programming Language :: Python :: 3.10
Classifier: Programming Language :: Python :: 3.11
Classifier: Programming Language :: Python :: 3.12
Requires-Dist: cachetools (>=5.4.0,<6.0.0)
Requires-Dist: dnspython (>=2.6.1,<3.0.0)
Requires-Dist: pydantic (>=2.6.3,<3.0.0)
Requires-Dist: requests (>=2.31.0,<3.0.0)
Requires-Dist: whois (>=1.20240129.2,<2.0.0)
